llmail/__init__.py
llmail/__main__.py
llmail/utils/__init__.py
llmail/utils/cli_args.py
llmail/utils/logging.py
llmail/utils/responding.py
llmail/utils/tracking.py
llmail/utils/utils.py
llmail-0.2.5.dist-info/entry_points.txt
llmail-0.2.5.dist-info/LICENSE
llmail-0.2.5.dist-info/METADATA
llmail-0.2.5.dist-info/WHEEL
llmail-0.2.5.dist-info/RECORD
