Metadata-Version: 2.1
Name: llmail
Version: 0.2.5
Summary: Interact with LLMs via email
Home-page: https://github.com/slashtechno/llmail
License: GNU Affero General Public License v3
Keywords: llm,email,ai,openai
Author: slashtechno
Author-email: 77907286+slashtechno@users.noreply.github.com
Requires-Python: >=3.10.0,<4.0.0
Classifier: License :: Other/Proprietary License
Classifier: Programming Language :: Python :: 3
Classifier: Programming Language :: Python :: 3.10
Classifier: Programming Language :: Python :: 3.11
Classifier: Programming Language :: Python :: 3.12
Requires-Dist: html2text (>=2024.2.26,<2025.0.0)
Requires-Dist: icecream (>=2.1.3,<3.0.0)
Requires-Dist: imapclient (>=3.0.1,<4.0.0)
Requires-Dist: loguru (>=0.7.2,<0.8.0)
Requires-Dist: openai (>=1.25.1,<2.0.0)
Requires-Dist: python-dotenv (>=1.0.1,<2.0.0)
Requires-Dist: yagmail[all] (>=0.15.293,<0.16.0)
Project-URL: Repository, https://github.com/slashtechno/llmail
